[
    {
        "level": 1,
        "title": "안전을 위해 주의하기",
        "page_num": 4,
        "hierarchy": [
            "안전을 위해 주의하기"
        ]
    },
    {
        "level": 2,
        "title": "제품을 사용하기 전에 읽어주세요.",
        "page_num": 4,
        "hierarchy": [
            "안전을 위해 주의하기",
            "제품을 사용하기 전에 읽어주세요."
        ]
    },
    {
        "level": 3,
        "title": "안전 기호와 의미",
        "page_num": 4,
        "hierarchy": [
            "안전을 위해 주의하기",
            "제품을 사용하기 전에 읽어주세요.",
            "안전 기호와 의미"
        ]
    },
    {
        "level": 3,
        "title": "R32 냉매 사용 제품(라벨)에 표시되는 안전 기호와 의미",
        "page_num": 4,
        "hierarchy": [
            "안전을 위해 주의하기",
            "제품을 사용하기 전에 읽어주세요.",
            "R32 냉매 사용 제품(라벨)에 표시되는 안전 기호와 의미"
        ]
    },
    {
        "level": 2,
        "title": "경고",
        "page_num": 4,
        "hierarchy": [
            "안전을 위해 주의하기",
            "경고"
        ]
    },
    {
        "level": 3,
        "title": "제품을 설치할 때",
        "page_num": 5,
        "hierarchy": [
            "안전을 위해 주의하기",
            "경고",
            "제품을 설치할 때"
        ]
    },
    {
        "level": 4,
        "title": "R 금지 사항",
        "page_num": 5,
        "hierarchy": [
            "안전을 위해 주의하기",
            "경고",
            "제품을 설치할 때",
            "R 금지 사항"
        ]
    },
    {
        "level": 4,
        "title": "j 준수 사항",
        "page_num": 5,
        "hierarchy": [
            "안전을 위해 주의하기",
            "경고",
            "제품을 설치할 때",
            "j 준수 사항"
        ]
    },
    {
        "level": 3,
        "title": "전원 플러그나 전원선을 다룰 때",
        "page_num": 5,
        "hierarchy": [
            "안전을 위해 주의하기",
            "경고",
            "전원 플러그나 전원선을 다룰 때"
        ]
    },
    {
        "level": 4,
        "title": "R 금지 사항",
        "page_num": 5,
        "hierarchy": [
            "안전을 위해 주의하기",
            "경고",
            "전원 플러그나 전원선을 다룰 때",
            "R 금지 사항"
        ]
    },
    {
        "level": 4,
        "title": "j 준수 사항",
        "page_num": 6,
        "hierarchy": [
            "안전을 위해 주의하기",
            "경고",
            "전원 플러그나 전원선을 다룰 때",
            "j 준수 사항"
        ]
    },
    {
        "level": 3,
        "title": "제품을 사용할 때",
        "page_num": 7,
        "hierarchy": [
            "안전을 위해 주의하기",
            "경고",
            "제품을 사용할 때"
        ]
    },
    {
        "level": 4,
        "title": "R 금지 사항",
        "page_num": 7,
        "hierarchy": [
            "안전을 위해 주의하기",
            "경고",
            "제품을 사용할 때",
            "R 금지 사항"
        ]
    },
    {
        "level": 4,
        "title": "j 준수 사항",
        "page_num": 7,
        "hierarchy": [
            "안전을 위해 주의하기",
            "경고",
            "제품을 사용할 때",
            "j 준수 사항"
        ]
    },
    {
        "level": 3,
        "title": "리모컨을 사용할 때",
        "page_num": 7,
        "hierarchy": [
            "안전을 위해 주의하기",
            "경고",
            "리모컨을 사용할 때"
        ]
    },
    {
        "level": 4,
        "title": "R 금지 사항",
        "page_num": 7,
        "hierarchy": [
            "안전을 위해 주의하기",
            "경고",
            "리모컨을 사용할 때",
            "R 금지 사항"
        ]
    },
    {
        "level": 4,
        "title": "j 준수 사항",
        "page_num": 7,
        "hierarchy": [
            "안전을 위해 주의하기",
            "경고",
            "리모컨을 사용할 때",
            "j 준수 사항"
        ]
    },
    {
        "level": 3,
        "title": "제품을 청소할 때",
        "page_num": 7,
        "hierarchy": [
            "안전을 위해 주의하기",
            "경고",
            "제품을 청소할 때"
        ]
    },
    {
        "level": 4,
        "title": "R 금지 사항",
        "page_num": 7,
        "hierarchy": [
            "안전을 위해 주의하기",
            "경고",
            "제품을 청소할 때",
            "R 금지 사항"
        ]
    },
    {
        "level": 4,
        "title": "j 준수 사항",
        "page_num": 8,
        "hierarchy": [
            "안전을 위해 주의하기",
            "경고",
            "제품을 청소할 때",
            "j 준수 사항"
        ]
    },
    {
        "level": 3,
        "title": "제품 이상 및 고장이 발생했을 때",
        "page_num": 8,
        "hierarchy": [
            "안전을 위해 주의하기",
            "경고",
            "제품 이상 및 고장이 발생했을 때"
        ]
    },
    {
        "level": 4,
        "title": "j 준수 사항",
        "page_num": 8,
        "hierarchy": [
            "안전을 위해 주의하기",
            "경고",
            "제품 이상 및 고장이 발생했을 때",
            "j 준수 사항"
        ]
    },
    {
        "level": 3,
        "title": "UVnano 기능을 사용할 때",
        "page_num": 8,
        "hierarchy": [
            "안전을 위해 주의하기",
            "경고",
            "UVnano 기능을 사용할 때"
        ]
    },
    {
        "level": 4,
        "title": "R 금지 사항",
        "page_num": 8,
        "hierarchy": [
            "안전을 위해 주의하기",
            "경고",
            "UVnano 기능을 사용할 때",
            "R 금지 사항"
        ]
    },
    {
        "level": 4,
        "title": "j 준수 사항",
        "page_num": 9,
        "hierarchy": [
            "안전을 위해 주의하기",
            "경고",
            "UVnano 기능을 사용할 때",
            "j 준수 사항"
        ]
    },
    {
        "level": 3,
        "title": "가연성 냉매(R32)를 다룰 때",
        "page_num": 9,
        "hierarchy": [
            "안전을 위해 주의하기",
            "경고",
            "가연성 냉매(R32)를 다룰 때"
        ]
    },
    {
        "level": 4,
        "title": "R 금지 사항",
        "page_num": 9,
        "hierarchy": [
            "안전을 위해 주의하기",
            "경고",
            "가연성 냉매(R32)를 다룰 때",
            "R 금지 사항"
        ]
    },
    {
        "level": 4,
        "title": "j 준수 사항",
        "page_num": 9,
        "hierarchy": [
            "안전을 위해 주의하기",
            "경고",
            "가연성 냉매(R32)를 다룰 때",
            "j 준수 사항"
        ]
    },
    {
        "level": 3,
        "title": "만일의 경우를 대비하여",
        "page_num": 9,
        "hierarchy": [
            "안전을 위해 주의하기",
            "경고",
            "만일의 경우를 대비하여"
        ]
    },
    {
        "level": 4,
        "title": "j 준수 사항",
        "page_num": 9,
        "hierarchy": [
            "안전을 위해 주의하기",
            "경고",
            "만일의 경우를 대비하여",
            "j 준수 사항"
        ]
    },
    {
        "level": 2,
        "title": "주의",
        "page_num": 9,
        "hierarchy": [
            "안전을 위해 주의하기",
            "주의"
        ]
    },
    {
        "level": 3,
        "title": "제품을 설치할 때",
        "page_num": 10,
        "hierarchy": [
            "안전을 위해 주의하기",
            "주의",
            "제품을 설치할 때"
        ]
    },
    {
        "level": 4,
        "title": "R 금지 사항",
        "page_num": 10,
        "hierarchy": [
            "안전을 위해 주의하기",
            "주의",
            "제품을 설치할 때",
            "R 금지 사항"
        ]
    },
    {
        "level": 4,
        "title": "j 준수 사항",
        "page_num": 10,
        "hierarchy": [
            "안전을 위해 주의하기",
            "주의",
            "제품을 설치할 때",
            "j 준수 사항"
        ]
    },
    {
        "level": 3,
        "title": "제품을 사용할 때",
        "page_num": 10,
        "hierarchy": [
            "안전을 위해 주의하기",
            "주의",
            "제품을 사용할 때"
        ]
    },
    {
        "level": 4,
        "title": "R 금지 사항",
        "page_num": 10,
        "hierarchy": [
            "안전을 위해 주의하기",
            "주의",
            "제품을 사용할 때",
            "R 금지 사항"
        ]
    },
    {
        "level": 4,
        "title": "j 준수 사항",
        "page_num": 10,
        "hierarchy": [
            "안전을 위해 주의하기",
            "주의",
            "제품을 사용할 때",
            "j 준수 사항"
        ]
    },
    {
        "level": 1,
        "title": "LG ThinQ 사용하기",
        "page_num": 11,
        "hierarchy": [
            "LG ThinQ 사용하기"
        ]
    },
    {
        "level": 2,
        "title": "LG ThinQ와 LG 가전 연결하기",
        "page_num": 11,
        "hierarchy": [
            "LG ThinQ 사용하기",
            "LG ThinQ와 LG 가전 연결하기"
        ]
    },
    {
        "level": 3,
        "title": "앱 설치 및 제품 등록하기",
        "page_num": 11,
        "hierarchy": [
            "LG ThinQ 사용하기",
            "LG ThinQ와 LG 가전 연결하기",
            "앱 설치 및 제품 등록하기"
        ]
    },
    {
        "level": 4,
        "title": "QR 코드가 부착된 제품",
        "page_num": 11,
        "hierarchy": [
            "LG ThinQ 사용하기",
            "LG ThinQ와 LG 가전 연결하기",
            "앱 설치 및 제품 등록하기",
            "QR 코드가 부착된 제품"
        ]
    },
    {
        "level": 4,
        "title": "QR 코드가 부착되지 않은 제품",
        "page_num": 11,
        "hierarchy": [
            "LG ThinQ 사용하기",
            "LG ThinQ와 LG 가전 연결하기",
            "앱 설치 및 제품 등록하기",
            "QR 코드가 부착되지 않은 제품"
        ]
    },
    {
        "level": 3,
        "title": "와이파이 모듈 사양",
        "page_num": 11,
        "hierarchy": [
            "LG ThinQ 사용하기",
            "LG ThinQ와 LG 가전 연결하기",
            "와이파이 모듈 사양"
        ]
    },
    {
        "level": 3,
        "title": "블루투스 모듈 사양",
        "page_num": 12,
        "hierarchy": [
            "LG ThinQ 사용하기",
            "LG ThinQ와 LG 가전 연결하기",
            "블루투스 모듈 사양"
        ]
    },
    {
        "level": 1,
        "title": "알아보기",
        "page_num": 13,
        "hierarchy": [
            "알아보기"
        ]
    },
    {
        "level": 2,
        "title": "에어컨의 모습과 기능 살펴보기",
        "page_num": 13,
        "hierarchy": [
            "알아보기",
            "에어컨의 모습과 기능 살펴보기"
        ]
    },
    {
        "level": 3,
        "title": "실내기",
        "page_num": 13,
        "hierarchy": [
            "알아보기",
            "에어컨의 모습과 기능 살펴보기",
            "실내기"
        ]
    },
    {
        "level": 3,
        "title": "실외기",
        "page_num": 14,
        "hierarchy": [
            "알아보기",
            "에어컨의 모습과 기능 살펴보기",
            "실외기"
        ]
    },
    {
        "level": 3,
        "title": "사용하기 전 알아두기",
        "page_num": 15,
        "hierarchy": [
            "알아보기",
            "에어컨의 모습과 기능 살펴보기",
            "사용하기 전 알아두기"
        ]
    },
    {
        "level": 1,
        "title": "사용하기",
        "page_num": 17,
        "hierarchy": [
            "사용하기"
        ]
    },
    {
        "level": 2,
        "title": "표시부 살펴보기",
        "page_num": 17,
        "hierarchy": [
            "사용하기",
            "표시부 살펴보기"
        ]
    },
    {
        "level": 3,
        "title": "실내기 표시부",
        "page_num": 17,
        "hierarchy": [
            "사용하기",
            "표시부 살펴보기",
            "실내기 표시부"
        ]
    },
    {
        "level": 2,
        "title": "리모컨 살펴보기",
        "page_num": 18,
        "hierarchy": [
            "사용하기",
            "리모컨 살펴보기"
        ]
    },
    {
        "level": 3,
        "title": "리모컨 건전지 끼우기",
        "page_num": 18,
        "hierarchy": [
            "사용하기",
            "리모컨 살펴보기",
            "리모컨 건전지 끼우기"
        ]
    },
    {
        "level": 3,
        "title": "리모컨의 신호 수신이 가능한 범위",
        "page_num": 18,
        "hierarchy": [
            "사용하기",
            "리모컨 살펴보기",
            "리모컨의 신호 수신이 가능한 범위"
        ]
    },
    {
        "level": 3,
        "title": "리모컨 처음 사용하기",
        "page_num": 19,
        "hierarchy": [
            "사용하기",
            "리모컨 살펴보기",
            "리모컨 처음 사용하기"
        ]
    },
    {
        "level": 2,
        "title": "냉방 기본 기능 작동하기",
        "page_num": 22,
        "hierarchy": [
            "사용하기",
            "냉방 기본 기능 작동하기"
        ]
    },
    {
        "level": 3,
        "title": "냉방 기능 사용하기",
        "page_num": 22,
        "hierarchy": [
            "사용하기",
            "냉방 기본 기능 작동하기",
            "냉방 기능 사용하기"
        ]
    },
    {
        "level": 3,
        "title": "냉방 부가 기능 설정하기",
        "page_num": 24,
        "hierarchy": [
            "사용하기",
            "냉방 기본 기능 작동하기",
            "냉방 부가 기능 설정하기"
        ]
    },
    {
        "level": 4,
        "title": "쿨파워 냉방",
        "page_num": 24,
        "hierarchy": [
            "사용하기",
            "냉방 기본 기능 작동하기",
            "냉방 부가 기능 설정하기",
            "쿨파워 냉방"
        ]
    },
    {
        "level": 4,
        "title": "간접바람",
        "page_num": 24,
        "hierarchy": [
            "사용하기",
            "냉방 기본 기능 작동하기",
            "냉방 부가 기능 설정하기",
            "간접바람"
        ]
    },
    {
        "level": 3,
        "title": "제습 기능 사용하기",
        "page_num": 25,
        "hierarchy": [
            "사용하기",
            "냉방 기본 기능 작동하기",
            "제습 기능 사용하기"
        ]
    },
    {
        "level": 3,
        "title": "제습 부가 기능 설정하기",
        "page_num": 26,
        "hierarchy": [
            "사용하기",
            "냉방 기본 기능 작동하기",
            "제습 부가 기능 설정하기"
        ]
    },
    {
        "level": 4,
        "title": "간접바람",
        "page_num": 26,
        "hierarchy": [
            "사용하기",
            "냉방 기본 기능 작동하기",
            "제습 부가 기능 설정하기",
            "간접바람"
        ]
    },
    {
        "level": 3,
        "title": "송풍 기능 사용하기",
        "page_num": 27,
        "hierarchy": [
            "사용하기",
            "냉방 기본 기능 작동하기",
            "송풍 기능 사용하기"
        ]
    },
    {
        "level": 3,
        "title": "송풍 부가 기능 설정하기",
        "page_num": 28,
        "hierarchy": [
            "사용하기",
            "냉방 기본 기능 작동하기",
            "송풍 부가 기능 설정하기"
        ]
    },
    {
        "level": 4,
        "title": "간접바람",
        "page_num": 28,
        "hierarchy": [
            "사용하기",
            "냉방 기본 기능 작동하기",
            "송풍 부가 기능 설정하기",
            "간접바람"
        ]
    },
    {
        "level": 2,
        "title": "편리한 기능",
        "page_num": 30,
        "hierarchy": [
            "사용하기",
            "편리한 기능"
        ]
    },
    {
        "level": 3,
        "title": "절전 냉방 기능 사용하기",
        "page_num": 30,
        "hierarchy": [
            "사용하기",
            "편리한 기능",
            "절전 냉방 기능 사용하기"
        ]
    },
    {
        "level": 3,
        "title": "스마트케어 기능 사용하기",
        "page_num": 30,
        "hierarchy": [
            "사용하기",
            "편리한 기능",
            "스마트케어 기능 사용하기"
        ]
    },
    {
        "level": 3,
        "title": "학습 정보 초기화하기",
        "page_num": 31,
        "hierarchy": [
            "사용하기",
            "편리한 기능",
            "학습 정보 초기화하기"
        ]
    },
    {
        "level": 2,
        "title": "추가 기능 및 설정하기",
        "page_num": 32,
        "hierarchy": [
            "사용하기",
            "추가 기능 및 설정하기"
        ]
    },
    {
        "level": 3,
        "title": "열대야 취침 설정하기",
        "page_num": 32,
        "hierarchy": [
            "사용하기",
            "추가 기능 및 설정하기",
            "열대야 취침 설정하기"
        ]
    },
    {
        "level": 4,
        "title": "설정 항목에서 열대야 취침 설정하기",
        "page_num": 32,
        "hierarchy": [
            "사용하기",
            "추가 기능 및 설정하기",
            "열대야 취침 설정하기",
            "설정 항목에서 열대야 취침 설정하기"
        ]
    },
    {
        "level": 4,
        "title": "열대야 취침 바로 설정하기",
        "page_num": 32,
        "hierarchy": [
            "사용하기",
            "추가 기능 및 설정하기",
            "열대야 취침 설정하기",
            "열대야 취침 바로 설정하기"
        ]
    },
    {
        "level": 3,
        "title": "켜짐 및 꺼짐 예약하기",
        "page_num": 33,
        "hierarchy": [
            "사용하기",
            "추가 기능 및 설정하기",
            "켜짐 및 꺼짐 예약하기"
        ]
    },
    {
        "level": 4,
        "title": "켜짐예약 설정하기",
        "page_num": 33,
        "hierarchy": [
            "사용하기",
            "추가 기능 및 설정하기",
            "켜짐 및 꺼짐 예약하기",
            "켜짐예약 설정하기"
        ]
    },
    {
        "level": 4,
        "title": "꺼짐 예약하기",
        "page_num": 33,
        "hierarchy": [
            "사용하기",
            "추가 기능 및 설정하기",
            "켜짐 및 꺼짐 예약하기",
            "꺼짐 예약하기"
        ]
    },
    {
        "level": 3,
        "title": "예약 취소하기",
        "page_num": 34,
        "hierarchy": [
            "사용하기",
            "추가 기능 및 설정하기",
            "예약 취소하기"
        ]
    },
    {
        "level": 4,
        "title": "예약 취소하기",
        "page_num": 34,
        "hierarchy": [
            "사용하기",
            "추가 기능 및 설정하기",
            "예약 취소하기",
            "예약 취소하기"
        ]
    },
    {
        "level": 3,
        "title": "스마트 진단하기",
        "page_num": 34,
        "hierarchy": [
            "사용하기",
            "추가 기능 및 설정하기",
            "스마트 진단하기"
        ]
    },
    {
        "level": 3,
        "title": "소리 크기 설정하기",
        "page_num": 35,
        "hierarchy": [
            "사용하기",
            "추가 기능 및 설정하기",
            "소리 크기 설정하기"
        ]
    },
    {
        "level": 3,
        "title": "화면 밝기 설정하기",
        "page_num": 36,
        "hierarchy": [
            "사용하기",
            "추가 기능 및 설정하기",
            "화면 밝기 설정하기"
        ]
    },
    {
        "level": 3,
        "title": "실내 온도 확인하기",
        "page_num": 37,
        "hierarchy": [
            "사용하기",
            "추가 기능 및 설정하기",
            "실내 온도 확인하기"
        ]
    },
    {
        "level": 3,
        "title": "전력량 확인하기(옵션)",
        "page_num": 37,
        "hierarchy": [
            "사용하기",
            "추가 기능 및 설정하기",
            "전력량 확인하기(옵션)"
        ]
    },
    {
        "level": 3,
        "title": "강제 운전 사용하기",
        "page_num": 38,
        "hierarchy": [
            "사용하기",
            "추가 기능 및 설정하기",
            "강제 운전 사용하기"
        ]
    },
    {
        "level": 3,
        "title": "정전 보상(자동 재운전) 기능 사용하기",
        "page_num": 38,
        "hierarchy": [
            "사용하기",
            "추가 기능 및 설정하기",
            "정전 보상(자동 재운전) 기능 사용하기"
        ]
    },
    {
        "level": 4,
        "title": "정전 보상 기능 설정하기",
        "page_num": 38,
        "hierarchy": [
            "사용하기",
            "추가 기능 및 설정하기",
            "정전 보상(자동 재운전) 기능 사용하기",
            "정전 보상 기능 설정하기"
        ]
    },
    {
        "level": 4,
        "title": "정전 보상 기능 해제하기",
        "page_num": 38,
        "hierarchy": [
            "사용하기",
            "추가 기능 및 설정하기",
            "정전 보상(자동 재운전) 기능 사용하기",
            "정전 보상 기능 해제하기"
        ]
    },
    {
        "level": 1,
        "title": "관리하기",
        "page_num": 40,
        "hierarchy": [
            "관리하기"
        ]
    },
    {
        "level": 2,
        "title": "청소하기",
        "page_num": 40,
        "hierarchy": [
            "관리하기",
            "청소하기"
        ]
    },
    {
        "level": 3,
        "title": "AI 건조 설정하기",
        "page_num": 40,
        "hierarchy": [
            "관리하기",
            "청소하기",
            "AI 건조 설정하기"
        ]
    },
    {
        "level": 3,
        "title": "UVnano 설정하기(옵션)",
        "page_num": 41,
        "hierarchy": [
            "관리하기",
            "청소하기",
            "UVnano 설정하기(옵션)"
        ]
    },
    {
        "level": 3,
        "title": "필터 청소하기",
        "page_num": 41,
        "hierarchy": [
            "관리하기",
            "청소하기",
            "필터 청소하기"
        ]
    },
    {
        "level": 4,
        "title": "필터 청소 주기",
        "page_num": 41,
        "hierarchy": [
            "관리하기",
            "청소하기",
            "필터 청소하기",
            "필터 청소 주기"
        ]
    },
    {
        "level": 4,
        "title": "필터 분리하기",
        "page_num": 42,
        "hierarchy": [
            "관리하기",
            "청소하기",
            "필터 청소하기",
            "필터 분리하기"
        ]
    },
    {
        "level": 4,
        "title": "극세 필터 청소하기",
        "page_num": 42,
        "hierarchy": [
            "관리하기",
            "청소하기",
            "필터 청소하기",
            "극세 필터 청소하기"
        ]
    },
    {
        "level": 4,
        "title": "필터 끼우기",
        "page_num": 43,
        "hierarchy": [
            "관리하기",
            "청소하기",
            "필터 청소하기",
            "필터 끼우기"
        ]
    },
    {
        "level": 3,
        "title": "열교환기 세척 기능 설정하기(옵션)",
        "page_num": 43,
        "hierarchy": [
            "관리하기",
            "청소하기",
            "열교환기 세척 기능 설정하기(옵션)"
        ]
    },
    {
        "level": 2,
        "title": "냄새 제거하기",
        "page_num": 45,
        "hierarchy": [
            "관리하기",
            "냄새 제거하기"
        ]
    },
    {
        "level": 3,
        "title": "냄새에 따른 제거 방법 알아보기",
        "page_num": 45,
        "hierarchy": [
            "관리하기",
            "냄새 제거하기",
            "냄새에 따른 제거 방법 알아보기"
        ]
    },
    {
        "level": 4,
        "title": "매캐하고 쾨쾨한 냄새",
        "page_num": 45,
        "hierarchy": [
            "관리하기",
            "냄새 제거하기",
            "냄새에 따른 제거 방법 알아보기",
            "매캐하고 쾨쾨한 냄새"
        ]
    },
    {
        "level": 4,
        "title": "플라스틱, 금속 냄새",
        "page_num": 45,
        "hierarchy": [
            "관리하기",
            "냄새 제거하기",
            "냄새에 따른 제거 방법 알아보기",
            "플라스틱, 금속 냄새"
        ]
    },
    {
        "level": 4,
        "title": "시큼함, 매움, 석유, 새집 냄새",
        "page_num": 45,
        "hierarchy": [
            "관리하기",
            "냄새 제거하기",
            "냄새에 따른 제거 방법 알아보기",
            "시큼함, 매움, 석유, 새집 냄새"
        ]
    },
    {
        "level": 4,
        "title": "음식 냄새",
        "page_num": 45,
        "hierarchy": [
            "관리하기",
            "냄새 제거하기",
            "냄새에 따른 제거 방법 알아보기",
            "음식 냄새"
        ]
    },
    {
        "level": 4,
        "title": "화장실, 하수구 냄새",
        "page_num": 45,
        "hierarchy": [
            "관리하기",
            "냄새 제거하기",
            "냄새에 따른 제거 방법 알아보기",
            "화장실, 하수구 냄새"
        ]
    },
    {
        "level": 2,
        "title": "보관하기",
        "page_num": 46,
        "hierarchy": [
            "관리하기",
            "보관하기"
        ]
    },
    {
        "level": 3,
        "title": "제품 보관하기",
        "page_num": 46,
        "hierarchy": [
            "관리하기",
            "보관하기",
            "제품 보관하기"
        ]
    },
    {
        "level": 4,
        "title": "송풍 운전으로 제품 내부 건조한 다음 보관하기",
        "page_num": 46,
        "hierarchy": [
            "관리하기",
            "보관하기",
            "제품 보관하기",
            "송풍 운전으로 제품 내부 건조한 다음 보관하기"
        ]
    },
    {
        "level": 1,
        "title": "고장 신고 전 확인하기",
        "page_num": 47,
        "hierarchy": [
            "고장 신고 전 확인하기"
        ]
    },
    {
        "level": 2,
        "title": "고장 진단하기",
        "page_num": 47,
        "hierarchy": [
            "고장 신고 전 확인하기",
            "고장 진단하기"
        ]
    },
    {
        "level": 3,
        "title": "LG ThinQ로 고장 진단하기",
        "page_num": 47,
        "hierarchy": [
            "고장 신고 전 확인하기",
            "고장 진단하기",
            "LG ThinQ로 고장 진단하기"
        ]
    },
    {
        "level": 3,
        "title": "신호음으로 고장 진단하기",
        "page_num": 47,
        "hierarchy": [
            "고장 신고 전 확인하기",
            "고장 진단하기",
            "신호음으로 고장 진단하기"
        ]
    },
    {
        "level": 2,
        "title": "문제 해결하기",
        "page_num": 48,
        "hierarchy": [
            "고장 신고 전 확인하기",
            "문제 해결하기"
        ]
    },
    {
        "level": 3,
        "title": "운전",
        "page_num": 48,
        "hierarchy": [
            "고장 신고 전 확인하기",
            "문제 해결하기",
            "운전"
        ]
    },
    {
        "level": 3,
        "title": "소음",
        "page_num": 50,
        "hierarchy": [
            "고장 신고 전 확인하기",
            "문제 해결하기",
            "소음"
        ]
    },
    {
        "level": 3,
        "title": "와이파이",
        "page_num": 50,
        "hierarchy": [
            "고장 신고 전 확인하기",
            "문제 해결하기",
            "와이파이"
        ]
    },
    {
        "level": 1,
        "title": "제품 보증서 보기",
        "page_num": 52,
        "hierarchy": [
            "제품 보증서 보기"
        ]
    },
    {
        "level": 2,
        "title": "제품 보증서",
        "page_num": 52,
        "hierarchy": [
            "제품 보증서 보기",
            "제품 보증서"
        ]
    },
    {
        "level": 3,
        "title": "품질 보증 기간",
        "page_num": 52,
        "hierarchy": [
            "제품 보증서 보기",
            "제품 보증서",
            "품질 보증 기간"
        ]
    },
    {
        "level": 3,
        "title": "소비자 분쟁 해결 기준",
        "page_num": 53,
        "hierarchy": [
            "제품 보증서 보기",
            "제품 보증서",
            "소비자 분쟁 해결 기준"
        ]
    },
    {
        "level": 3,
        "title": "고객이 비용을 내야 하는 유상 서비스에 대한 책임",
        "page_num": 54,
        "hierarchy": [
            "제품 보증서 보기",
            "제품 보증서",
            "고객이 비용을 내야 하는 유상 서비스에 대한 책임"
        ]
    },
    {
        "level": 4,
        "title": "최초 제품 설치 이후 고객의 요구로 제품 위치를 바꾸거나, 이사 후 재설치한 경우",
        "page_num": 54,
        "hierarchy": [
            "제품 보증서 보기",
            "제품 보증서",
            "고객이 비용을 내야 하는 유상 서비스에 대한 책임",
            "최초 제품 설치 이후 고객의 요구로 제품 위치를 바꾸거나, 이사 후 재설치한 경우"
        ]
    },
    {
        "level": 1,
        "title": "부록",
        "page_num": 55,
        "hierarchy": [
            "부록"
        ]
    },
    {
        "level": 2,
        "title": "에너지 효율 등급",
        "page_num": 55,
        "hierarchy": [
            "부록",
            "에너지 효율 등급"
        ]
    },
    {
        "level": 3,
        "title": "제품 에너지 효율 등급 안내",
        "page_num": 55,
        "hierarchy": [
            "부록",
            "에너지 효율 등급",
            "제품 에너지 효율 등급 안내"
        ]
    },
    {
        "level": 2,
        "title": "폐가전제품 처리 절차",
        "page_num": 55,
        "hierarchy": [
            "부록",
            "폐가전제품 처리 절차"
        ]
    },
    {
        "level": 3,
        "title": "신제품을 구입했을 때",
        "page_num": 55,
        "hierarchy": [
            "부록",
            "폐가전제품 처리 절차",
            "신제품을 구입했을 때"
        ]
    },
    {
        "level": 3,
        "title": "사용하던 제품을 버릴 때",
        "page_num": 55,
        "hierarchy": [
            "부록",
            "폐가전제품 처리 절차",
            "사용하던 제품을 버릴 때"
        ]
    },
    {
        "level": 2,
        "title": "오픈소스 정보",
        "page_num": 55,
        "hierarchy": [
            "부록",
            "오픈소스 정보"
        ]
    },
    {
        "level": 3,
        "title": "오픈소스 안내 정보",
        "page_num": 55,
        "hierarchy": [
            "부록",
            "오픈소스 정보",
            "오픈소스 안내 정보"
        ]
    },
    {
        "level": 2,
        "title": "제품 규격",
        "page_num": 55,
        "hierarchy": [
            "부록",
            "제품 규격"
        ]
    },
    {
        "level": 3,
        "title": "UVnano 모듈 정보(옵션)",
        "page_num": 55,
        "hierarchy": [
            "부록",
            "제품 규격",
            "UVnano 모듈 정보(옵션)"
        ]
    },
    {
        "level": 2,
        "title": "생활 속 전기안전 캠페인",
        "page_num": 56,
        "hierarchy": [
            "부록",
            "생활 속 전기안전 캠페인"
        ]
    },
    {
        "level": 3,
        "title": "우리 집 전기시설 안전사용 요령",
        "page_num": 56,
        "hierarchy": [
            "부록",
            "생활 속 전기안전 캠페인",
            "우리 집 전기시설 안전사용 요령"
        ]
    },
    {
        "level": 3,
        "title": "우리 집 전기안전을 위한 기본 수칙(동영상)",
        "page_num": 56,
        "hierarchy": [
            "부록",
            "생활 속 전기안전 캠페인",
            "우리 집 전기안전을 위한 기본 수칙(동영상)"
        ]
    }
]